hydroquebec/__init__.py
hydroquebec/api.py
hydroquebec-0.1.0.dist-info/METADATA
hydroquebec-0.1.0.dist-info/WHEEL
hydroquebec-0.1.0.dist-info/top_level.txt
hydroquebec-0.1.0.dist-info/RECORD
